mentos/__init__.py
mentos/connection.py
mentos/exceptions.py
mentos/executor.py
mentos/interface.py
mentos/retry.py
mentos/scheduler.py
mentos/states.py
mentos/subscription.py
mentos/utils.py
mentos-0.1.8.dist-info/DESCRIPTION.rst
mentos-0.1.8.dist-info/METADATA
mentos-0.1.8.dist-info/RECORD
mentos-0.1.8.dist-info/WHEEL
mentos-0.1.8.dist-info/metadata.json
mentos-0.1.8.dist-info/top_level.txt
mentos-0.1.8.dist-info/zip-safe
