Metadata-Version: 2.0
Name: mentos
Version: 0.1.8
Summary: Fresh Python Mesos HTTP Scheduler and Executor
Home-page: http://github.com/arttii/mentos
Author: Artyom Topchyan
Author-email: a.topchyan@reply.de
License: Apache License, Version 2.0
Keywords: mesos scheduler executor http distributed
Platform: UNKNOWN
Classifier: Intended Audience :: Developers
Classifier: License :: OSI Approved :: Apache Software License
Classifier: Programming Language :: Python :: 2.7
Classifier: Programming Language :: Python :: 3
Requires-Dist: six
Requires-Dist: toolz
Requires-Dist: tornado
Requires-Dist: zoonado
